{
  "batch_id": "github_0013",
  "source": "github",
  "commit_count": 20,
  "commits": [
    {
      "sha": "97e785d5",
      "message": "fix(TPT-2375): Fix React 18 hydration Suspense boundary error (#60941)\n\n- Wrap SkuDataGuard setTimeout state updates in startTransition\n- Wrap FunnelPlansSelection Redux dispatch in startTransition\n- Prevents concurrent updates during hydration process\n- Fixes Sentry issue WEB-A3JW affecting ~100 users\n- Addresses startTransition requirement for React 18 concurrent features\n\n[Cursor_Code]",
      "author": "oliverstr",
      "author_email": "oliver_str@hotmail.com",
      "date": "2025-11-24T13:26:35Z",
      "url": "https://github.com/hellofresh/web/commit/97e785d5644166e4ca391d59f1d2e68e73933750",
      "repo": "hellofresh/web",
      "matched_prefix": "TPT-"
    },
    {
      "sha": "64943060",
      "message": "[TPT-2282] contentful entry name update (#60949)",
      "author": "vmanukyan03",
      "author_email": "vmanukyan@griddynamics.com",
      "date": "2025-11-24T12:49:17Z",
      "url": "https://github.com/hellofresh/web/commit/6494306007460562affcf3dc0e05902548fa686f",
      "repo": "hellofresh/web",
      "matched_prefix": "TPT-"
    },
    {
      "sha": "4f3583cd",
      "message": "[GOC-3381] Implement OTP Statsig Event on Checkout Success (#60889)\n\n* implement otp statsig event\n\n* adjust tests\n\n* update payments app config tests",
      "author": "Madeeha Hasan",
      "author_email": "33419910+madeeha96@users.noreply.github.com",
      "date": "2025-11-24T11:20:27Z",
      "url": "https://github.com/hellofresh/web/commit/4f3583cd9a6439c5347da823d223cdd01eaaf1cf",
      "repo": "hellofresh/web",
      "matched_prefix": "GOC-"
    },
    {
      "sha": "1a3530be",
      "message": "[TPT-2282] portion percentage contentful keys added (#60940)",
      "author": "vmanukyan03",
      "author_email": "vmanukyan@griddynamics.com",
      "date": "2025-11-24T10:50:36Z",
      "url": "https://github.com/hellofresh/web/commit/1a3530be3cf12a67c23775bde3d5497fc6e772a6",
      "repo": "hellofresh/web",
      "matched_prefix": "TPT-"
    },
    {
      "sha": "28f912b4",
      "message": "[TPT-2358] Dictionaries (#60817)",
      "author": "Max Burov",
      "author_email": "mabu@hellofresh.com",
      "date": "2025-11-24T10:49:50Z",
      "url": "https://github.com/hellofresh/web/commit/28f912b4d19e738c986c31d45fb88a92d33b4486",
      "repo": "hellofresh/web",
      "matched_prefix": "TPT-"
    },
    {
      "sha": "46c6b13b",
      "message": "[TPT-2357] Consolidating product family types used for PetsTable (#60860)\n\n* [TPT-2357] Consolidate product family types to single source of truth\n\n* [TPT-2357] Simplify useGetMixProductProteins to use CORE_TYPES directly and fix test mocks",
      "author": "Guhan Sundararajan",
      "author_email": "gsun@hellofresh.com",
      "date": "2025-11-24T09:20:23Z",
      "url": "https://github.com/hellofresh/web/commit/46c6b13be708454676a4fc028bc8a95e5adfb5fa",
      "repo": "hellofresh/web",
      "matched_prefix": "TPT-"
    },
    {
      "sha": "017820f9",
      "message": "[GOC-3390] Adds redirections (#60871)",
      "author": "Pamela Plúas",
      "author_email": "pamepluas@gmail.com",
      "date": "2025-11-24T08:55:10Z",
      "url": "https://github.com/hellofresh/web/commit/017820f9146f428bc28f3e89429202f015ac3f7e",
      "repo": "hellofresh/web",
      "matched_prefix": "GOC-"
    },
    {
      "sha": "91791d54",
      "message": "[RTEVMS-2301] Remove hardcoded delivery interval (#60829)",
      "author": "Jan Cássio",
      "author_email": "110180472+jancassiohf@users.noreply.github.com",
      "date": "2025-11-21T20:16:55Z",
      "url": "https://github.com/hellofresh/web/commit/91791d54f77c0495b4deb128ce80182fd2a0767e",
      "repo": "hellofresh/web",
      "matched_prefix": "RTEVMS-"
    },
    {
      "sha": "9cd913c0",
      "message": "[RTEVMS-2255] Factor Form | OTP order summary logic (#60769)\n\n* adding otp cart items to header cart\n\n* update sub-brand cart qty\n\n* hide frequency\n\n* reorder imports\n\n* add otp products to order summary\n\n* adding otp values to cart context\n\n* add global atom for unified spaces\n\n* remove import violation\n\n* fix WCAG compliance\n\n* fix tests\n\n* use local storage\n\n* fix unit tests\n\n* skip failing units\n\n* remove redundant context value and fix OTP list ui\n\n* remove mock\n\n* fix unit tests\n\n* fix max qty\n\n* fix order summary rendering of OTP items",
      "author": "Emily Stanek",
      "author_email": "89855438+eshellofresh@users.noreply.github.com",
      "date": "2025-11-21T20:07:27Z",
      "url": "https://github.com/hellofresh/web/commit/9cd913c0cc8280770380777a955b7ca0e6812837",
      "repo": "hellofresh/web",
      "matched_prefix": "RTEVMS-"
    },
    {
      "sha": "69ecdbae",
      "message": "[TPT-2106] Refactor multipet checkout test (#60862)",
      "author": "Ellen",
      "author_email": "elen.margaryan@ext.hellofresh.com",
      "date": "2025-11-21T14:14:34Z",
      "url": "https://github.com/hellofresh/web/commit/69ecdbae6158d19e7dd5939ee799803a982622fb",
      "repo": "hellofresh/web",
      "matched_prefix": "TPT-"
    },
    {
      "sha": "9e355c78",
      "message": "[GOC-3292] Add surcharge value into cart service function adapter (#60856)",
      "author": "Romina Nicastro",
      "author_email": "rominicastro@gmail.com",
      "date": "2025-11-21T13:40:48Z",
      "url": "https://github.com/hellofresh/web/commit/9e355c7880d450e3ac8d3e49c1edbb7327f07e9b",
      "repo": "hellofresh/web",
      "matched_prefix": "GOC-"
    },
    {
      "sha": "8d821bb4",
      "message": "[TPT-2298] tpt_portion_percentage experiment flag integrated (#60581)\n\n* [TPT-2298] tpt_portion_percentage experiment flag integrated\n\n* [TPT-2298] ts issue fix\n\n* [TPT-2298] new quiz step hidden behind experiment\n\n* [TPT-2298] new quiz question removed from retake-quiz flow\n\n* [TPT-2298] test fixes\n\n* [TPT-2298] /retake-quiz flow test case added\n\n* [TPT-2298] retake and multipet flows separated\n\n* [TPT-2298] test fix\n\n* [TPT-2298] test update\n\n* [TPT-2298] test updated\n\n* [TPT-2298] unit test updated",
      "author": "vmanukyan03",
      "author_email": "vmanukyan@griddynamics.com",
      "date": "2025-11-21T11:42:25Z",
      "url": "https://github.com/hellofresh/web/commit/8d821bb4606b3df5953dd1f6148144841d3e344e",
      "repo": "hellofresh/web",
      "matched_prefix": "TPT-"
    },
    {
      "sha": "35aec54e",
      "message": "[TPT-2357] Deprecating WL useFormattedCurrency util (#60822)",
      "author": "Guhan Sundararajan",
      "author_email": "gsun@hellofresh.com",
      "date": "2025-11-21T09:06:48Z",
      "url": "https://github.com/hellofresh/web/commit/35aec54ee156831cd863e48a8d3e7dd1396ae5ec",
      "repo": "hellofresh/web",
      "matched_prefix": "TPT-"
    },
    {
      "sha": "cca9422a",
      "message": "TPT-2208 - add contentful keys for key ingredients (#60845)",
      "author": "Mariia Oleksiuk",
      "author_email": "155674255+moleksiuk-gd@users.noreply.github.com",
      "date": "2025-11-21T08:25:47Z",
      "url": "https://github.com/hellofresh/web/commit/cca9422a23c8a4690ef3a99d5446a9a456c47386",
      "repo": "hellofresh/web",
      "matched_prefix": "TPT-"
    },
    {
      "sha": "f1777fcc",
      "message": "[TPT-2333]: Refactor constants (#60800)\n\n* [TPT-2333]: refactor constants\n\n* revies fixes",
      "author": "anastasiiaaiuvdzhy-hf",
      "author_email": "anastasiia.aiuvdzhy@ext.hellofresh.com",
      "date": "2025-11-21T08:09:32Z",
      "url": "https://github.com/hellofresh/web/commit/f1777fcc86bcb8e311af3b9f30105a2d970fcc01",
      "repo": "hellofresh/web",
      "matched_prefix": "TPT-"
    },
    {
      "sha": "d5716244",
      "message": "[GOC-3295] Returns PriceWithPricePerServing in useReactivationPricing hook (#60824)\n\n* [GOC-3295] Returns PriceWithPricePerServing in useReactivationPricing\n\n* [GOC-3295] Fixes tests",
      "author": "Pamela Plúas",
      "author_email": "pamepluas@gmail.com",
      "date": "2025-11-21T07:54:24Z",
      "url": "https://github.com/hellofresh/web/commit/d5716244ff806049211d2c0097a069208e230295",
      "repo": "hellofresh/web",
      "matched_prefix": "GOC-"
    },
    {
      "sha": "1660a03c",
      "message": "[TPT-2259] updated the source of delivery for reschedule delivery cdps payload (#60749)",
      "author": "matborowiak",
      "author_email": "mateusz.borowiak@hellofresh.com",
      "date": "2025-11-20T16:25:44Z",
      "url": "https://github.com/hellofresh/web/commit/1660a03cb8fa6e9295c3a04588b716eb39b99ef1",
      "repo": "hellofresh/web",
      "matched_prefix": "TPT-"
    },
    {
      "sha": "7eab3ebe",
      "message": "[GOC-3295] Includes prices per serving (#60765)\n\n* [GOC-3295] Renames discount\n\n* [GOC-3295] Adds new model\n\n* [GOC-3295] Removes overload in hook and create new hook\n\n* [GOC-3295] Returns Prices with serving in useGetReactivationPrices\n\n* [GOC-3295] Fixes tests\n\n* [GOC-3295] Updates tests\n\n* [GOC-3295] Move calculations to model factory",
      "author": "Pamela Plúas",
      "author_email": "pamepluas@gmail.com",
      "date": "2025-11-20T15:42:26Z",
      "url": "https://github.com/hellofresh/web/commit/7eab3ebec1070081b6ca6706478770e1801dffb9",
      "repo": "hellofresh/web",
      "matched_prefix": "GOC-"
    },
    {
      "sha": "61d2dffe",
      "message": "[TPT-2358] Initial setup of kn-box-model-builder (#60803)",
      "author": "Max Burov",
      "author_email": "mabu@hellofresh.com",
      "date": "2025-11-20T15:04:58Z",
      "url": "https://github.com/hellofresh/web/commit/61d2dffedf5b0a8059a03fb4a1fa32a16764017b",
      "repo": "hellofresh/web",
      "matched_prefix": "TPT-"
    },
    {
      "sha": "624f5512",
      "message": "TPT-2207: add descriptio contentful keys (#60802)\n\nCo-authored-by: alugovtsev <Andrey.Lugovtsev@macys.com>",
      "author": "alugovtsev-hf",
      "author_email": "andrey.lugovtsev@ext.hellofresh.com",
      "date": "2025-11-20T14:20:59Z",
      "url": "https://github.com/hellofresh/web/commit/624f551231af18e1e83bb7bf1004fdcebd8ddbd0",
      "repo": "hellofresh/web",
      "matched_prefix": "TPT-"
    }
  ],
  "date_range": {
    "oldest": "2025-11-20T14:20:59Z",
    "newest": "2025-11-24T13:26:35Z"
  }
}