{
  "batch_id": "C06CT0185T3_1751384371.954219",
  "channel_name": "tribe-new-ventures-leads-internal",
  "channel_id": "C06CT0185T3",
  "message_count": 15,
  "analyzed_at": "2026-01-02T13:00:48.972430",
  "decisions": [
    {
      "what": "Delay FTC cancellation funnel changes, implement only conversion funnel checkbox on Monday",
      "who": [
        "U03UMPD2NNS",
        "Legal",
        "U07VDFEFBQU"
      ],
      "date": "Week 29 (July 2025)",
      "context": "Legal approval obtained to delay TPT checkout changes until August 18th due to conflicting initiative; GoodChop aligned to follow same timeline",
      "confidence": "high"
    },
    {
      "what": "Focus next 2 sprints on Wallet add-on persistence and P0 monitoring/alerting, with remaining engineers improving stability",
      "who": [
        "U07VDFEFBQU",
        "U027201FQSV",
        "U03TY4YJU4X"
      ],
      "date": "Week 29 (July 2025)",
      "context": "To solve TR issues and improve observability before hearing issues from stakeholders; 2-week cadence experiment can be handled by 2 engineers",
      "confidence": "high"
    },
    {
      "what": "Prioritize PATCH /subscriptions deprecation for CDPS migration in next sprint (mid-August deadline)",
      "who": [
        "UEZ4PRFKM",
        "U027201FQSV",
        "U8F7ZDAPM"
      ],
      "date": "Week 29 (July 2025)",
      "context": "Consumer Core rolling out CDPS and deprecating old endpoint; originally requested end of July but negotiated to mid-August",
      "confidence": "medium"
    },
    {
      "what": "Decline Kiro test license trial",
      "who": [
        "U027201FQSV",
        "U03TY4YJU4X"
      ],
      "date": "Week 30 (July 2025)",
      "context": "Would be too disruptive for team at this point in time",
      "confidence": "high"
    }
  ],
  "entities": [
    {
      "name": "GoodChop (GoC)",
      "type": "brand",
      "context": "New venture brand with checkout, delivery, and monitoring implementations",
      "relationships": [
        "U027201FQSV",
        "U01AKGWGLC8",
        "U07VDFEFBQU",
        "GoodChop Squad"
      ]
    },
    {
      "name": "The Pets Table (TPT)",
      "type": "brand",
      "context": "New venture brand with separate checkout implementation and FTC compliance work",
      "relationships": [
        "U03UMPD2NNS",
        "U8F7ZDAPM",
        "U7SJ525DE",
        "The Pets Table Squad"
      ]
    },
    {
      "name": "CDPS (Customer Delivery Platform Service)",
      "type": "system",
      "context": "New platform being rolled out by Consumer Core requiring API migration",
      "relationships": [
        "Consumer Core",
        "PATCH /subscriptions API"
      ]
    },
    {
      "name": "New Ventures Systems Squad (NVS)",
      "type": "squad",
      "context": "Squad handling cross-cutting concerns for new ventures",
      "relationships": [
        "U2D54V0UV"
      ]
    },
    {
      "name": "Cross-selling & PUMA Squad",
      "type": "squad",
      "context": "Squad working on cross-selling initiatives and ABBA",
      "relationships": [
        "U01TQGXG9D3",
        "U03R6F2AG9K",
        "U05BNQPJX4K",
        "U01KPB90WQM"
      ]
    },
    {
      "name": "Anomaly Detection Dashboard",
      "type": "system",
      "context": "Grafana-based monitoring system for GA events implemented for GoodChop, partially for TPT",
      "relationships": [
        "U027201FQSV",
        "U068H5475SP",
        "Observability Initiative"
      ]
    }
  ],
  "blockers": [
    {
      "description": "Multiple high-priority API deprecations competing for sprint capacity (PATCH /subscriptions and /calculate/batch)",
      "owner": "U8F7ZDAPM",
      "status": "active",
      "impact": "TPT squad capacity stretched across multiple urgent migrations with mid-August deadlines"
    },
    {
      "description": "Wallet add-on persistence causing TR (transaction) issues",
      "owner": "U07VDFEFBQU",
      "status": "active",
      "impact": "Affecting reliability; being prioritized in current and next sprint"
    },
    {
      "description": "Overlapping Tuesday afternoon meetings causing confusion",
      "owner": "UEZ4PRFKM",
      "status": "resolved",
      "impact": "Meeting conflicts clarified; leads meeting to be evaluated for priority and scope alignment"
    }
  ],
  "action_items": [
    {
      "task": "Complete IT CAP spreadsheet",
      "owner": "All squads",
      "due": "Week 29/30",
      "status": "done"
    },
    {
      "task": "Update Weekly Team Update Notes before Monday standup",
      "owner": "All squad leads",
      "due": "Weekly (Monday)",
      "status": "pending"
    },
    {
      "task": "Create ticket for PATCH /subscriptions migration (GOC-3035)",
      "owner": "U027201FQSV",
      "due": "Week 29",
      "status": "done"
    },
    {
      "task": "Implement FTC conversion funnel checkbox on checkout",
      "owner": "U03UMPD2NNS",
      "due": "Monday Week 29",
      "status": "pending"
    },
    {
      "task": "Implement FTC checkout changes for TPT",
      "owner": "U03UMPD2NNS",
      "due": "August 18th",
      "status": "pending"
    },
    {
      "task": "Prioritize /calculate/batch endpoint deprecation for TPT",
      "owner": "U8F7ZDAPM",
      "due": "Next sprint",
      "status": "pending"
    },
    {
      "task": "Set up Anomaly Detection for TPT with U068H5475SP",
      "owner": "U03UMPD2NNS",
      "due": "After vacation",
      "status": "pending"
    },
    {
      "task": "Verify if DPLAT-2364 cadence bug affects GoodChop and TPT",
      "owner": "U01AKGWGLC8, U03UMPD2NNS",
      "due": "Week 30",
      "status": "done"
    }
  ],
  "key_context": [
    {
      "topic": "FTC Compliance Rollout",
      "summary": "Legal compliance changes for checkout and cancellation funnels being rolled out across brands with staggered timelines. TPT delaying to August 18th while HF already launched July 7th.",
      "relevance": "Critical regulatory compliance work affecting customer-facing flows across all new venture brands"
    },
    {
      "topic": "CDPS Migration",
      "summary": "Consumer Core deprecating legacy subscription APIs requiring migration work across GoC and TPT with mid-August deadline. Multiple competing deprecations creating capacity constraints.",
      "relevance": "Platform-wide technical debt requiring immediate attention to avoid breaking changes"
    },
    {
      "topic": "Observability and Stability Focus",
      "summary": "Teams shifting focus to P0 monitoring, alerting, and bug fixes after experiencing reliability issues. GoodChop has implemented anomaly detection dashboard; TPT exploring adoption.",
      "relevance": "Proactive approach to catch issues before stakeholders report them, improving operational maturity"
    },
    {
      "topic": "Sprint Planning and Capacity",
      "summary": "Teams balancing feature work with technical debt, migrations, and stability improvements. Experimenting with 2-week cadence and dedicated stability sprints.",
      "relevance": "Reflects maturation of new ventures from pure feature development to sustainable operations"
    }
  ],
  "summary": "New Ventures teams coordinating FTC compliance rollouts, CDPS API migrations, and stability improvements while managing competing priorities and sprint capacity across GoodChop and The Pets Table brands."
}