{
  "topic": "TPT Mobile App - Push Notifications and Engagement Features",
  "timestamp": "2026-01-05T13:29:23.877312",
  "sources_searched": [
    "brain",
    "jira",
    "github",
    "slack",
    "gdrive",
    "confluence"
  ],
  "results": {
    "brain": [
      {
        "source": "brain",
        "type": "inbox",
        "path": "AI_Guidance/Brain/Inbox/Archive/INBOX_2025-12-10-.md",
        "title": "INBOX 2025-12-10-",
        "excerpt": "Recipe Development](https://docs.google.com/spreadsheets/d/1V8VPcFcI6fy9OPLgY6UL96aaK9_k5XCs3Ltk2lKtPTc/edit?usp=drivesdk) | Modified: 2025-12-10 | Owner: Abby Spellman\n- [DOC] [[VIEW ONLY] F_ Meal & Add On Database](https://docs.google.com/spreadsheets/d/1a1155pX94RJf_pZmz_bWmwFom2bhD3HrRLAqclhs3Z",
        "relevance_score": 10433,
        "last_modified": "2025-12-17T21:44:43.372131",
        "_source": "brain"
      },
      {
        "source": "brain",
        "type": "inbox",
        "path": "AI_Guidance/Brain/Inbox/INBOX_2025-12-23-.md",
        "title": "INBOX 2025-12-23-",
        "excerpt": "Recipe Development](https://docs.google.com/spreadsheets/d/1V8VPcFcI6fy9OPLgY6UL96aaK9_k5XCs3Ltk2lKtPTc/edit?usp=drivesdk) | Modified: 2025-12-22 | Owner: Abby Spellman\n- [DOC] [Your Virtual Interview with HelloFresh | [TECH-CA] Staff Engineer - Frontend [TAM] - 2025/12/22 06:50 EST - Notes by Gemi",
        "relevance_score": 9244,
        "last_modified": "2025-12-25T02:22:50.886971",
        "_source": "brain"
      },
      {
        "source": "brain",
        "type": "inbox",
        "path": "AI_Guidance/Brain/Inbox/Archive/INBOX_2025-12-05-.md",
        "title": "INBOX 2025-12-05-",
        "excerpt": "Recipe Development](https://docs.google.com/spreadsheets/d/1V8VPcFcI6fy9OPLgY6UL96aaK9_k5XCs3Ltk2lKtPTc/edit?usp=drivesdk) | Modified: 2025-12-05 | Owner: Abby Spellman\n- [DOC] [CMA Squad overview](https://docs.google.com/spreadsheets/d/1q55kO1Nku3iw5y1G2XfNX2O1bDXiRaJ8vYWEHoRkBlY/edit?usp=drivesdk",
        "relevance_score": 9119,
        "last_modified": "2025-12-10T02:52:22.415976",
        "_source": "brain"
      },
      {
        "source": "brain",
        "type": "inbox",
        "path": "AI_Guidance/Brain/Inbox/Archive/INBOX_2025-12-18-.md",
        "title": "INBOX 2025-12-18-",
        "excerpt": "Recipe Development](https://docs.google.com/spreadsheets/d/1V8VPcFcI6fy9OPLgY6UL96aaK9_k5XCs3Ltk2lKtPTc/edit?usp=drivesdk) | Modified: 2025-12-17 | Owner: Abby Spellman\n- [DOC] [Notes - The Pets Table - Weekly Check-in](https://docs.google.com/document/d/1vOrUixt-zxfpCL9iVGENlw9TfCNcnqeUuyfrsHBvKKI",
        "relevance_score": 9110,
        "last_modified": "2025-12-19T23:38:50.537216",
        "_source": "brain"
      },
      {
        "source": "brain",
        "type": "inbox",
        "path": "AI_Guidance/Brain/Inbox/INBOX_2025-12-19-.md",
        "title": "INBOX 2025-12-19-",
        "excerpt": "Recipe Development](https://docs.google.com/spreadsheets/d/1V8VPcFcI6fy9OPLgY6UL96aaK9_k5XCs3Ltk2lKtPTc/edit?usp=drivesdk) | Modified: 2025-12-19 | Owner: Abby Spellman\n- [DOC] [New Ventures - Operational Overhead Calculation](https://docs.google.com/spreadsheets/d/1U0JsuosUV33kTNDrRMNijBtI_FnazVa_",
        "relevance_score": 9086,
        "last_modified": "2025-12-19T23:38:50.538246",
        "_source": "brain"
      },
      {
        "source": "brain",
        "type": "inbox",
        "path": "AI_Guidance/Brain/Inbox/INBOX_2025-12-17-.md",
        "title": "INBOX 2025-12-17-",
        "excerpt": "lhyXrdQN3OyXl8-l94cp33g/edit?usp=drivesdk) | Modified: 2025-12-16 | Owner: Nikita Gorshkov\n- [DOC] [TPT_App_v1_Proposal.md](https://docs.google.com/document/d/1UKvgQEtRESrFsGRlkLDw-jH3c5aZVJ_8W1vwsIPUtIc/edit?usp=drivesdk) | Modified: 2025-12-16 | Owner: Nikita Gorshkov\n- [DOC] [Prateek:Nikita 1:1 -",
        "relevance_score": 8667,
        "last_modified": "2025-12-17T21:44:43.381146",
        "_source": "brain"
      },
      {
        "source": "brain",
        "type": "inbox",
        "path": "AI_Guidance/Brain/Inbox/Archive/INBOX_2025-12-09-.md",
        "title": "INBOX 2025-12-09-",
        "excerpt": "Recipe Development](https://docs.google.com/spreadsheets/d/1V8VPcFcI6fy9OPLgY6UL96aaK9_k5XCs3Ltk2lKtPTc/edit?usp=drivesdk) | Modified: 2025-12-09 | Owner: Abby Spellman\n- [DOC] [2025 HelloTech OKR management tool](https://docs.google.com/spreadsheets/d/1jdRyu6eoWAyossWaGCbXEu_rrmuxWWRWni5Mzy2FLBM/e",
        "relevance_score": 8503,
        "last_modified": "2025-12-10T02:39:09.470654",
        "_source": "brain"
      },
      {
        "source": "brain",
        "type": "inbox",
        "path": "AI_Guidance/Brain/Inbox/INBOX_2025-12-30-.md",
        "title": "INBOX 2025-12-30-",
        "excerpt": "Recipe Development](https://docs.google.com/spreadsheets/d/1V8VPcFcI6fy9OPLgY6UL96aaK9_k5XCs3Ltk2lKtPTc/edit?usp=drivesdk) | Modified: 2025-12-29 | Owner: Abby Spellman\n- [DOC] [Notes: Hamed <> Nikita 1:1](https://docs.google.com/document/d/1HWhfmd_VP-8REbk3u9nEybAJ4-sfeoXegVHuQcc0INM/edit?usp=driv",
        "relevance_score": 8498,
        "last_modified": "2026-01-02T09:36:19.737813",
        "_source": "brain"
      },
      {
        "source": "brain",
        "type": "inbox",
        "path": "AI_Guidance/Brain/Inbox/Archive/INBOX_2025-12-16-.md",
        "title": "INBOX 2025-12-16-",
        "excerpt": "pmsX7DtYHNp8ONlYcZQnpk4/edit?usp=drivesdk) | Modified: 2025-12-15 | Owner: Nikita Gorshkov\n- [DOC] [TPT App: Discovery](https://docs.google.com/spreadsheets/d/1njFgQemZhGmDz-TTDX75BckUov66opHGp1Ay3gE8U8k/edit?usp=drivesdk) | Modified: 2025-12-15 | Owner: Nikita Gorshkov\n- [DOC] [HFCA - CCM Recipes](",
        "relevance_score": 8490,
        "last_modified": "2025-12-17T21:44:43.375355",
        "_source": "brain"
      },
      {
        "source": "brain",
        "type": "inbox",
        "path": "AI_Guidance/Brain/Inbox/Archive/INBOX_2025-12-08-02.md",
        "title": "INBOX 2025-12-08-02",
        "excerpt": "Recipe Development](https://docs.google.com/spreadsheets/d/1V8VPcFcI6fy9OPLgY6UL96aaK9_k5XCs3Ltk2lKtPTc/edit?usp=drivesdk) | Modified: 2025-12-08 | Owner: Abby Spellman\n- [DOC] [HFCA - CCM Recipes](https://docs.google.com/spreadsheets/d/1ifyitYmONU5VnTW8MjP4dlVo_h3IQKWJzK4AfhoIndU/edit?usp=drivesdk",
        "relevance_score": 7306,
        "last_modified": "2025-12-10T02:39:09.469430",
        "_source": "brain"
      }
    ],
    "jira": [],
    "github": [],
    "slack": [],
    "gdrive": [],
    "confluence": []
  },
  "total_results": 10,
  "summary": {
    "topic": "TPT Mobile App - Push Notifications and Engagement Features",
    "sources_with_results": [
      "brain"
    ],
    "top_items": [
      {
        "source": "brain",
        "title": "INBOX 2025-12-10-",
        "type": "inbox",
        "score": 10433
      },
      {
        "source": "brain",
        "title": "INBOX 2025-12-23-",
        "type": "inbox",
        "score": 9244
      },
      {
        "source": "brain",
        "title": "INBOX 2025-12-05-",
        "type": "inbox",
        "score": 9119
      },
      {
        "source": "brain",
        "title": "INBOX 2025-12-18-",
        "type": "inbox",
        "score": 9110
      },
      {
        "source": "brain",
        "title": "INBOX 2025-12-19-",
        "type": "inbox",
        "score": 9086
      }
    ],
    "total_results": 10
  }
}